chall_check/__init__.py
chall_check/cli.py
chall_check/md.py
cyber_skyline_chall_check-0.5.1.dist-info/licenses/LICENSE
cyber_skyline_chall_check-0.5.1.dist-info/METADATA
cyber_skyline_chall_check-0.5.1.dist-info/WHEEL
cyber_skyline_chall_check-0.5.1.dist-info/entry_points.txt
cyber_skyline_chall_check-0.5.1.dist-info/top_level.txt
cyber_skyline_chall_check-0.5.1.dist-info/RECORD
