Metadata-Version: 2.4
Name: cyber-skyline-chall-check
Version: 0.5.1
Summary: Add your description here
Requires-Python: >=3.12
License-File: LICENSE
Requires-Dist: cyber-skyline-chall-parser
Requires-Dist: pyyaml>=6.0.2
Requires-Dist: typer>=0.16.0
Dynamic: license-file
